{
  "67":{
    "eventId":67, "attributes":[
      {
        "eventId":67, "attribute":"cool", "percent":20
      }
    ],
    "characters":[
      {
        "eventId":67, "characterId":11, "percent":10, "seq":5
      },
      {
        "eventId":67, "characterId":12, "percent":10, "seq":2
      },
      {
        "eventId":67, "characterId":13, "percent":10, "seq":3
      },
      {
        "eventId":67, "characterId":14, "percent":10, "seq":4
      },
      {
        "eventId":67, "characterId":15, "percent":10, "seq":1
      }
    ],
    "stories":[
      {
        "eventId":67, "seq":0, "caption":"オープニング", "title":"反省会", "synopsis":"バンド練習のあとの反省会。\n美咲の表情は少しだけ沈んでいるようで……", "scenarioId":"event67-01", "coverImage":"67_0", "backgroundImage":"271", "releasePt":0, "releaseConditions":"オープニングシナリオ", "rewards":[
          {
            "id":1017, "eventId":67, "seq":0, "rewardType":"item", "rewardId":13, "rewardQuantity":1
          },
          {
            "id":1018, "eventId":67, "seq":0, "rewardType":"star", "rewardQuantity":50
          }
        ]
      },
      {
        "eventId":67, "seq":1, "caption":"第１話", "title":"デジャブ", "synopsis":"親とケンカしたことに落ち込む美咲。\nそんな美咲に薫が声を掛け……", "scenarioId":"event67-02", "coverImage":"67_1", "backgroundImage":"272", "releasePt":3000, "releaseConditions":"3000イベントP達成", "rewards":[
          {
            "id":1019, "eventId":67, "seq":1, "rewardType":"item", "rewardId":13, "rewardQuantity":1
          },
          {
            "id":1020, "eventId":67, "seq":1, "rewardType":"star", "rewardQuantity":50
          }
        ]
      },
      {
        "eventId":67, "seq":2, "caption":"第２話", "title":"薫の部屋", "synopsis":"薫の部屋にやってきた美咲。\nそこにメンバーから連絡が入り……", "scenarioId":"event67-03", "coverImage":"67_2", "backgroundImage":"273", "releasePt":6000, "releaseConditions":"6000イベントP達成", "rewards":[
          {
            "id":1021, "eventId":67, "seq":2, "rewardType":"item", "rewardId":13, "rewardQuantity":1
          },
          {
            "id":1022, "eventId":67, "seq":2, "rewardType":"star", "rewardQuantity":50
          }
        ]
      },
      {
        "eventId":67, "seq":3, "caption":"第３話", "title":"お泊りのスタイル", "synopsis":"薫の部屋にお泊りすることとなった\nハロハピメンバー。それぞれの手荷物は……", "scenarioId":"event67-04", "coverImage":"67_3", "backgroundImage":"273", "releasePt":15000, "releaseConditions":"15000イベントP達成", "rewards":[
          {
            "id":1023, "eventId":67, "seq":3, "rewardType":"item", "rewardId":13, "rewardQuantity":1
          },
          {
            "id":1024, "eventId":67, "seq":3, "rewardType":"star", "rewardQuantity":50
          }
        ]
      },
      {
        "eventId":67, "seq":4, "caption":"第４話", "title":"夕食のあとに", "synopsis":"薫の家で夕食を食べた一同。\n就寝前の楽しいひとときが始まる", "scenarioId":"event67-05", "coverImage":"67_4", "backgroundImage":"273", "releasePt":28000, "releaseConditions":"28000イベントP達成", "rewards":[
          {
            "id":1025, "eventId":67, "seq":4, "rewardType":"item", "rewardId":13, "rewardQuantity":1
          },
          {
            "id":1026, "eventId":67, "seq":4, "rewardType":"star", "rewardQuantity":50
          }
        ]
      },
      {
        "eventId":67, "seq":5, "caption":"第５話", "title":"儚き夜", "synopsis":"なかなか寝付けない美咲。\n薫が語りかけた言葉とは……", "scenarioId":"event67-06", "coverImage":"67_5", "backgroundImage":"274", "releasePt":40000, "releaseConditions":"40000イベントP達成", "rewards":[
          {
            "id":1027, "eventId":67, "seq":5, "rewardType":"item", "rewardId":13, "rewardQuantity":1
          },
          {
            "id":1028, "eventId":67, "seq":5, "rewardType":"star", "rewardQuantity":50
          }
        ]
      },
      {
        "eventId":67, "seq":6, "caption":"エンディング", "title":"スタート地点", "synopsis":"親に電話をかける美咲。\nその電話で重大なことを告げられ……", "scenarioId":"event67-07", "coverImage":"67_6", "backgroundImage":"275", "releasePt":55000, "releaseConditions":"55000イベントP達成", "rewards":[
          {
            "id":1029, "eventId":67, "seq":6, "rewardType":"item", "rewardId":13, "rewardQuantity":1
          },
          {
            "id":1030, "eventId":67, "seq":6, "rewardType":"star", "rewardQuantity":50
          }
        ]
      }
    ]
  }
}
