[
  {
    "eventId":1, "introduction":"桜が満開の季節。ポピパのみんなで帰っていると、イヴやこころ達と出会う。少し変わったメンバーばかりで心配する有咲をよそに、みんなでお花見をすることになって…？", "resourceSetName":"characters/resourceset/res001005", "resourceFileName":"card_normal", "logoResourceSetName":"event/sakura/images", "logoResourceFileName":"logo"
  },
  {
    "eventId":2, "introduction":"友希那は、偶然父親の歌うテープを発見する。Roseliaのメンバーはその曲を次のライブで演奏しようと盛り上がるが…", "resourceSetName":"characters/resourceset/res021005", "resourceFileName":"card_normal", "logoResourceSetName":"event/father/images", "logoResourceFileName":"logo"
  },
  {
    "eventId":3, "introduction":"こころの突然の思い付きで豪華客船に乗ることになったハロハピ。船上で夜景などを楽しんでいたメンバーだったが、突然謎の人物が現れ…", "resourceSetName":"characters/resourceset/res011006", "resourceFileName":"card_normal", "logoResourceSetName":"event/thief/images", "logoResourceFileName":"logo"
  },
  {
    "eventId":4, "introduction":"生徒会長の七菜からグリグリのバースデーライブに出ないかと誘われたりみ。ライブまで1週間しかない中で、りみはポピパのメンバーにある提案をして…？", "resourceSetName":"characters/resourceset/res003005", "resourceFileName":"card_normal", "logoResourceSetName":"event/glitter/images", "logoResourceFileName":"logo"
  },
  {
    "eventId":5, "introduction":"香澄はつぐみ、蘭を誘って天体観測ツアーに行くことに。途中で偶然出会った日菜、こころも合流して一緒に流星群を見に行くけれど…？", "resourceSetName":"characters/resourceset/res017005", "resourceFileName":"card_normal", "logoResourceSetName":"event/twinkle/images", "logoResourceFileName":"logo"
  },
  {
    "eventId":6, "introduction":"Afterglowが初めて録音したCDを見つけたひまり。\nメンバー全員で曲を聴くと、３年前の懐かしい記憶がよみがえってきて――", "resourceSetName":"characters/resourceset/res006006", "resourceFileName":"card_normal", "logoResourceSetName":"event/evening/images", "logoResourceFileName":"logo"
  },
  {
    "eventId":7, "introduction":"放課後、たえと有咲が教室で練習していると、女生徒の悲鳴が響き渡る――！飼育しているうさぎが校内に逃げてしまったと聞き、２人が後を追うと…？", "resourceSetName":"characters/resourceset/res002006", "resourceFileName":"card_normal", "logoResourceSetName":"event/rabbit/images", "logoResourceFileName":"logo"
  },
  {
    "eventId":8, "introduction":"憧れのアイドルグループが解散すると聞いて、ひどく落ち込む彩。パスパレのメンバーは彩を励まそうとして…？", "resourceSetName":"characters/resourceset/res016005", "resourceFileName":"card_normal", "logoResourceSetName":"event/future/images", "logoResourceFileName":"logo"
  },
  {
    "eventId":9, "introduction":"結婚式の宣伝写真を撮るため、新婦役のモデルになってほしいと頼まれた沙綾。緊張が隠せない沙綾の前に、新郎役のあの人が現れて…？", "resourceSetName":"characters/resourceset/res004006", "resourceFileName":"card_normal", "logoResourceSetName":"event/wedding/images", "logoResourceFileName":"logo"
  },
  {
    "eventId":10, "introduction":"リサが急用でRoseliaの練習を抜けてしまい、４人で練習するメンバー。いつも通りに練習を始めたのに、普段と違う出来事が起こって…？", "resourceSetName":"characters/resourceset/res023006", "resourceFileName":"card_normal", "logoResourceSetName":"event/losslisa/images", "logoResourceFileName":"logo"
  },
  {
    "eventId":11, "introduction":"商店街で七夕祭りが行われることになり、紗夜を誘った日菜。紗夜は断るものの、思いがけない出来事が起こって…？", "resourceSetName":"characters/resourceset/res022007", "resourceFileName":"card_normal", "logoResourceSetName":"event/tanabata2017/images", "logoResourceFileName":"logo"
  },
  {
    "eventId":12, "introduction":"風邪を引いてしまった巴は、薬を買ってきてほしいとあこにメールをする。それを受けて、あこは自分が姉のお世話をすると固く決心して…？", "resourceSetName":"characters/resourceset/res024008", "resourceFileName":"card_normal", "logoResourceSetName":"event/nursing/images", "logoResourceFileName":"logo"
  },
  {
    "eventId":13, "introduction":"とある舞台に出演することになった千聖。千聖は自分なりに役づくりをして稽古に臨むが、稽古中、演出家から意外な事を言われて…？", "resourceSetName":"characters/resourceset/res018007", "resourceFileName":"card_normal", "logoResourceSetName":"event/tsubomi/images", "logoResourceFileName":"logo"
  },
  {
    "eventId":14, "introduction":"Afterglowみんなで海へ行こうと提案するひまり。メンバー全員に断られてしまうが、諦めきれないひまりはとある人物に電話をして…？", "resourceSetName":"characters/resourceset/res025007", "resourceFileName":"card_normal", "logoResourceSetName":"event/svacation2017/images", "logoResourceFileName":"logo"
  },
  {
    "eventId":15, "introduction":"香澄の提案で花火大会に行くことにしたPoppin'Party。「良い場所を知ってる」という有咲を頼りに進むが、人混みに飲まれ散り散りになって…", "resourceSetName":"characters/resourceset/res005008", "resourceFileName":"card_normal", "logoResourceSetName":"event/hanabi2017/images", "logoResourceFileName":"logo"
  },
  {
    "eventId":16, "introduction":"夏休みももう終盤。宿題が終わらないというひまりは教室に大変なものを忘れてきてしまって…！？", "resourceSetName":"characters/resourceset/res006008", "resourceFileName":"card_normal", "logoResourceSetName":"event/afterglow_six/images", "logoResourceFileName":"logo"
  },
  {
    "eventId":17, "introduction":"羽丘女子学園の文化祭。薫は、演劇部の公演に千聖を客演として呼ぶことを提案。二人はロミオとジュリエットを演じることになり…？", "resourceSetName":"characters/resourceset/res018009", "resourceFileName":"card_normal", "logoResourceSetName":"event/chisato_kaoru_festival/images", "logoResourceFileName":"logo"
  },
  {
    "eventId":18, "introduction":"こころ達と仲がいいことをクラスメイトに指摘された美咲。急な出来事に美咲はその場でとっさの嘘をついてしまい…？", "resourceSetName":"characters/resourceset/res015009", "resourceFileName":"card_normal", "logoResourceSetName":"event/hello_world2017/images", "logoResourceFileName":"logo"
  },
  {
    "eventId":19, "introduction":"テレビでの特番が決定したパスパレ。その内容は無人島でミッションをクリアせよ、という内容で…！？", "resourceSetName":"characters/resourceset/res019010", "resourceFileName":"card_normal", "logoResourceSetName":"event/unpopulated_island/images", "logoResourceFileName":"logo"
  },
  {
    "eventId":20, "introduction":"ハロウィン前日に、こころがみんなと楽しいことがしたいと美咲に提案して…？", "resourceSetName":"characters/resourceset/res011013", "resourceFileName":"card_normal", "logoResourceSetName":"event/halloween_2017/images", "logoResourceFileName":"logo"
  },
  {
    "eventId":21, "introduction":"以前より少し距離が縮まった紗夜と日菜。テレビで放送されたパスパレのライブを見て、紗夜はとあることを感じ…？", "resourceSetName":"characters/resourceset/res022009", "resourceFileName":"card_normal", "logoResourceSetName":"event/autumn_drizzle_2017/images", "logoResourceFileName":"logo"
  },
  {
    "eventId":22, "introduction":"待ちに待った年に一度の花女の体育祭。スポーツが大好きなはぐみは、誰よりもやる気満々！…と思いきや、何やら曇った表情。", "resourceSetName":"characters/resourceset/res013011", "resourceFileName":"card_normal", "logoResourceSetName":"event/smile_anchor/images", "logoResourceFileName":"logo"
  },
  {
    "eventId":23, "introduction":"羽沢珈琲店で開催されるお菓子教室を手伝うことになったつぐみ。当日、意外な参加者が現れて…！？", "resourceSetName":"characters/resourceset/res010012", "resourceFileName":"card_normal", "logoResourceSetName":"event/sweet_suite/images", "logoResourceFileName":"logo"
  },
  {
    "eventId":24, "introduction":"フィンランドの友達が日本に遊びにくることを知ったイヴ。来日を楽しみに思いながらも、気になることがあるようで…？", "resourceSetName":"characters/resourceset/res020013", "resourceFileName":"card_normal", "logoResourceSetName":"event/home_party_2017/images", "logoResourceFileName":"logo"
  },
  {
    "eventId":25, "introduction":"Roseliaのために、何かできることはないかと考えるリサは、とあるコンテストへの挑戦を思いつき…？", "resourceSetName":"characters/resourceset/res021013", "resourceFileName":"card_normal", "logoResourceSetName":"event/someday_deliver/images", "logoResourceFileName":"logo"
  },
  {
    "eventId":26, "introduction":"突如、開催されることになったクリスマスライブ。最高の聖夜にするため、有咲はあることを思いついたようで…", "resourceSetName":"characters/resourceset/res005012", "resourceFileName":"card_normal", "logoResourceSetName":"event/happy_poppin_2017/images", "logoResourceFileName":"logo"
  },
  {
    "eventId":27, "introduction":"バンドの練習中、Pastel＊Palettesの日菜から蘭にメールが届く。それは、パスパレに曲を提供してほしいというもので…？", "resourceSetName":"characters/resourceset/res006014", "resourceFileName":"card_normal", "logoResourceSetName":"event/azure_2017/images", "logoResourceFileName":"logo"
  },
  {
    "eventId":28, "introduction":"とあるきっかけで、水族館へ行くことになったハロハピ一同。そこへ向かう途中、迷子のペンギンを見かけて…？", "resourceSetName":"characters/resourceset/res014013", "resourceFileName":"card_normal", "logoResourceSetName":"event/little_smile_step/images", "logoResourceFileName":"logo"
  },
  {
    "eventId":29, "introduction":"新春の訪れと共に、初詣へとやってきたこころと美咲。そこで偶然出くわしたイヴやあこ達とおみくじを引いてみたところ…", "resourceSetName":"characters/resourceset/res020014", "resourceFileName":"card_normal", "logoResourceSetName":"event/new_year_2018/images", "logoResourceFileName":"logo"
  },
  {
    "eventId":30, "introduction":"各地のライブハウスが集うイベントに参加することとなった香澄達。ポピパをイベントに推薦したまりなには、ある考えがあるようで…", "resourceSetName":"characters/resourceset/res001016", "resourceFileName":"card_normal", "logoResourceSetName":"event/circling_2018/images", "logoResourceFileName":"logo"
  },
  {
    "eventId":31, "introduction":"あこの希望でオンラインゲームをやることになったRoselia。ゲームの操作に戸惑うメンバー達は無事にクエストをクリアできるのか？", "resourceSetName":"characters/resourceset/res025014", "resourceFileName":"card_normal", "logoResourceSetName":"event/roselia_rpg/images", "logoResourceFileName":"logo"
  },
  {
    "eventId":32, "introduction":"バレンタインデーに友チョコ交換会をすることになったポピパのメンバー。初めて友達にチョコを贈ることになった有咲だが、思わぬトラブルが発生…！", "resourceSetName":"characters/resourceset/res023016", "resourceFileName":"card_normal", "logoResourceSetName":"event/happy_valentine_2018/images", "logoResourceFileName":"logo"
  },
  {
    "eventId":33, "introduction":"スノボがしたいとはしゃぐ、はぐみ。ノリノリのあこや日菜に、美咲や運動音痴の麻弥まで巻き込んで一同は雪山へと向かう。", "resourceSetName":"characters/resourceset/res019014", "resourceFileName":"card_normal", "logoResourceSetName":"event/winter_sports_2018/images", "logoResourceFileName":"logo"
  },
  {
    "eventId":34, "introduction":"新曲のCDリリースイベントをすることとなった、パスパレメンバー。様々な気持ちを胸に、初めてのお渡し会が始まる！ファンとの交流で、日菜が気づくこととは…？", "resourceSetName":"characters/resourceset/res017016", "resourceFileName":"card_normal", "logoResourceSetName":"event/wonderful_others/images", "logoResourceFileName":"logo"
  },
  {
    "eventId":35, "introduction":"子猫ちゃん達へのお返しに悩んでいた薫。偶然会ったひまりの一言から、ミュージカルをすることに。多くの人達を巻き込んだ計画は果たして成功するのか？", "resourceSetName":"characters/resourceset/res012015", "resourceFileName":"card_normal", "logoResourceSetName":"event/white_day_2018/images", "logoResourceFileName":"logo"
  },
  {
    "eventId":36, "introduction":"普段はあまり見ることのできない各バンドのライブ前後の様子。華やかなステージのその裏で、彼女達が交わす会話とは…？", "resourceSetName":"characters/resourceset/res001019", "resourceFileName":"card_normal", "logoResourceSetName":"event/back_stage_pass/images", "logoResourceFileName":"logo"
  },
  {
    "eventId":37, "introduction":"冬の海を見に、小旅行に行くことにしたAfterglow。食事や観光を楽しむが、行く先々でトラブルが発生し…？", "resourceSetName":"characters/resourceset/res009016", "resourceFileName":"card_normal", "logoResourceSetName":"event/evening_2018/images", "logoResourceFileName":"logo"
  },
  {
    "eventId":38, "introduction":"あこの何気ない一言がきっかけで部活の体験入部をすることにした燐子。偶然居合わせた紗夜とともに、様々な部活にチャレンジしてみるが…？", "resourceSetName":"characters/resourceset/res025015", "resourceFileName":"card_normal", "logoResourceSetName":"event/fresh_verdure_2018/images", "logoResourceFileName":"logo"
  },
  {
    "eventId":39, "introduction":"リリースイベントを行っていたパスパレ。そのイベント中に起こったある出来事をきっかけにファンの仲が悪くなっていく。そんな状況の中、イヴのとった行動とは…？", "resourceSetName":"characters/resourceset/res020023", "resourceFileName":"card_normal", "logoResourceSetName":"event/bushido_2018/images", "logoResourceFileName":"logo"
  },
  {
    "eventId":40, "introduction":"ひょんなことから、ふわキャラ選手権に出場することになったミッシェル。活躍が期待される中、強力なライバルが現れて…？", "resourceSetName":"characters/resourceset/res014020", "resourceFileName":"card_normal", "logoResourceSetName":"event/fuwa_chara_2018/images", "logoResourceFileName":"logo"
  },
  {
    "eventId":42, "introduction":"お気に入りのマンガが最終回を迎え、ため息をこぼすモカ。そんなモカを励ますため、つぐみが行った提案とは…？", "resourceSetName":"characters/resourceset/res010022", "resourceFileName":"card_normal", "logoResourceSetName":"event/girls_anthology_2018/images", "logoResourceFileName":"logo"
  },
  {
    "eventId":44, "introduction":"長雨の季節。響く太鼓の音に誘われ、神社へとやってきたこころ達。そこには和太鼓の練習をしている巴の姿が…", "resourceSetName":"characters/resourceset/res009022", "resourceFileName":"card_normal", "logoResourceSetName":"event/beat_rain_2018/images", "logoResourceFileName":"logo"
  },
  {
    "eventId":45, "introduction":"校内清掃で同じグループになった薫、リサ、麻弥、日菜、蘭の５人。割り当てられた清掃場所の近くには、不気味な噂を持つ井戸があって…？", "resourceSetName":"characters/resourceset/res023023", "resourceFileName":"card_normal", "logoResourceSetName":"event/well_ghost_2018/images", "logoResourceFileName":"logo"
  },
  {
    "eventId":47, "introduction":"いつも気の合う香澄とはぐみ。二人は子供の頃、公園で一緒に遊んでいた友達だった。忘れかけた思い出を手がかりに、その公園を探しに出かけるが…", "resourceSetName":"characters/resourceset/res013020", "resourceFileName":"card_normal", "logoResourceSetName":"event/tanabata2018/images", "logoResourceFileName":"logo"
  },
  {
    "eventId":48, "introduction":"こころの屋敷で見つけた古い地図。そこに描かれていたのは骸骨マークと、とある場所に付けられたバツ印…これはもしかして宝の地図！？", "resourceSetName":"characters/resourceset/res014021", "resourceFileName":"card_normal", "logoResourceSetName":"event/treasure_hunt_2018/images", "logoResourceFileName":"logo"
  },
  {
    "eventId":49, "introduction":"『心の怪盗団』の噂を聞き、自分たちも怪盗団になることにしたAfterglow。そんな彼女達の元に届いた『宝を盗んでみよ』というハロハッピーからの挑戦状…", "resourceSetName":"characters/resourceset/res006022", "resourceFileName":"card_normal", "logoResourceSetName":"event/persona2018/images", "logoResourceFileName":"logo"
  },
  {
    "eventId":50, "introduction":"テストも終わり、ようやく夏休み。はぐみの提案で海に行くことになった有咲は、普段と違う顔ぶれにちょっと緊張気味。おまけに海では、予想外の展開に…！？", "resourceSetName":"characters/resourceset/res020025", "resourceFileName":"card_normal", "logoResourceSetName":"event/summer_dive_2018/images", "logoResourceFileName":"logo"
  },
  {
    "eventId":51, "introduction":"あこからRoseliaのライブに招待された巴。あこの成長を楽しみにしていた巴だったが、ライブを観た後はなんだか複雑な様子で…？", "resourceSetName":"characters/resourceset/res024022", "resourceFileName":"card_normal", "logoResourceSetName":"event/grow_up_2018/images", "logoResourceFileName":"logo"
  },
  {
    "eventId":52, "introduction":"夏の終わりが近づくこの季節。Roseliaが訪れたのは人気のテーマパーク。Roseliaとは縁遠そうな場所で、彼女達はどんな思い出を作るのか…？", "resourceSetName":"characters/resourceset/res021022", "resourceFileName":"card_normal", "logoResourceSetName":"event/rose_summer_2018/images", "logoResourceFileName":"logo"
  },
  {
    "eventId":53, "introduction":"夏休み中にやり残したことを解消しようとショッピングモールへとやってきたポピパ。お買い物、映画鑑賞、カラオケ…そんな何気ない日常に、たくさんの笑顔があふれ…", "resourceSetName":"characters/resourceset/res004019", "resourceFileName":"card_normal", "logoResourceSetName":"event/popi_holiday_2018/images", "logoResourceFileName":"logo"
  },
  {
    "eventId":55, "introduction":"２駅隣にカフェができたと聞き、一緒に出かける花音と千聖。しかし、たったの２駅も方向音痴と電車音痴にはちょっとした冒険で…", "resourceSetName":"characters/resourceset/res014022", "resourceFileName":"card_normal", "logoResourceSetName":"event/promenade_2018/images", "logoResourceFileName":"logo"
  },
  {
    "eventId":56, "introduction":"西洋の古城をイメージした豪華ホテルへとやってきたパスパレのメンバー。レポーターの仕事と聞かされて来たものの、大広間の扉は突然閉ざされ…", "resourceSetName":"characters/resourceset/res017023", "resourceFileName":"card_normal", "logoResourceSetName":"event/trick_or_escape!_2018/images", "logoResourceFileName":"logo"
  },
  {
    "eventId":58, "introduction":"とある休日。有咲はふと見掛けた蘭とひまりに声をかけようとするが、あまり話したことのない二人に、どう声をかけていいのかわからず…", "resourceSetName":"characters/resourceset/res005026", "resourceFileName":"card_normal", "logoResourceSetName":"event/otaria_2018/images", "logoResourceFileName":"logo"
  },
  {
    "eventId":59, "introduction":"羽丘演劇部の定期公演に参加することとなった燐子達。演劇を表から創る薫、裏から支える麻弥、それぞれのこだわりを目の当たりにして…", "resourceSetName":"characters/resourceset/res019024", "resourceFileName":"card_normal", "logoResourceSetName":"event/butai_mezot_2018/images", "logoResourceFileName":"logo"
  },
  {
    "eventId":60, "introduction":"些細なきっかけで衝突することになったRoseliaとAfterglow。その決着を２マンライブでつけることになって…！？", "resourceSetName":"characters/resourceset/res021024", "resourceFileName":"card_normal", "logoResourceSetName":"event/rose_vs_aflo/images", "logoResourceFileName":"logo"
  },
  {
    "eventId":61, "introduction":"大好きな商店街を盛り上げるための曲を作ることになったポピパ。順調に作詞を進める香澄の隣で、りみは思わぬスランプに陥ってしまい…", "resourceSetName":"characters/resourceset/res003022", "resourceFileName":"card_normal", "logoResourceSetName":"event/rimi_fight_song/images", "logoResourceFileName":"logo"
  },
  {
    "eventId":62, "introduction":"毎年恒例になっているクリスマスパーティの話題で盛り上がるAfterglow。話題は幼少期までさかのぼり…！？", "resourceSetName":"characters/resourceset/res007024", "resourceFileName":"card_normal", "logoResourceSetName":"event/aflo_christmas/images", "logoResourceFileName":"logo"
  },
  {
    "eventId":63, "introduction":"商店街主催のフリーマーケットに参加することになったはぐみとひまり。フリマ経験者？のりみにも声をかけ、三人で準備を始めるのだが…。", "resourceSetName":"characters/resourceset/res013025", "resourceFileName":"card_normal", "logoResourceSetName":"event/winter_sky_marche/images", "logoResourceFileName":"logo"
  },
  {
    "eventId":64, "introduction":"部員は日菜ひとりながらも楽しく活動をする羽丘天文部。ところが、そんな天文部に廃部の危機が訪れてしまう…！果たして部を存続させることはできるのか？", "resourceSetName":"characters/resourceset/res022023", "resourceFileName":"card_normal", "logoResourceSetName":"event/twin_star_ensemble/images", "logoResourceFileName":"logo"
  },
  {
    "eventId":65, "introduction":"新年の訪れとともにガールズバンドパーティのメンバーがCiRCLEに大集合！メインイベントのかくし芸大会は、なんと全員参加…！？", "resourceSetName":"characters/resourceset/res001029", "resourceFileName":"card_normal", "logoResourceSetName":"event/hidden_talent_2018/images", "logoResourceFileName":"logo"
  },
  {
    "eventId":66, "introduction":"アイドル雑誌でのコラム連載を引き受けた麻弥。『アイドルらしい記事』を書くため、保留にしていた『自分にとってのアイドル像』と向き合う決意をするのだが…？", "resourceSetName":"characters/resourceset/res019025", "resourceFileName":"card_normal", "logoResourceSetName":"event/maya_self_confidence/images", "logoResourceFileName":"logo"
  },
  {
    "eventId":67, "introduction":"ハロー、ハッピーワールド！の練習後の反省会、どこか上の空の美咲。親とケンカ中だった美咲は、薫の家に泊まらせてもらうことに。そこに他のメンバーも加わって…？", "resourceSetName":"characters/resourceset/res015031", "resourceFileName":"card_normal", "logoResourceSetName":"event/ephemeral_night_dream/images", "logoResourceFileName":"logo"
  },
  {
    "eventId":68, "introduction":"バンドのメンバーに『最高の友チョコ』を贈ると宣言したひまり。花音や彩たちと行ったチョコの祭典会場で、ひまりが見つけたものとは…？", "resourceSetName":"characters/resourceset/res008027", "resourceFileName":"card_normal", "logoResourceSetName":"event/for_whom_chocolate/images", "logoResourceFileName":"logo"
  },
  {
    "eventId":69, "introduction":"日曜日の商店街。沙綾と巴は休日を楽しいものにしようと、商店街に住むメンバーを誘って遊びに出かける計画を立てるが…", "resourceSetName":"characters/resourceset/res004023", "resourceFileName":"card_normal", "logoResourceSetName":"event/holiday_street/images", "logoResourceFileName":"logo"
  },
  {
    "eventId":70, "introduction":"ピアノのコンクールに挑戦することとなった燐子。しかし、発表された課題曲は燐子にとって因縁のある曲。過去を乗り越えるために、燐子は自分のピアノと向き合う…！", "resourceSetName":"characters/resourceset/res025024", "resourceFileName":"card_normal", "logoResourceSetName":"event/rinko_piano/images", "logoResourceFileName":"logo"
  },
  {
    "eventId":71, "introduction":"久々のオフをどう過ごそうかぼんやり考えている千聖の前に突然たえが現れて…気づけば千聖の予想もつかないような賑やかな１日に！？", "resourceSetName":"characters/resourceset/res002024", "resourceFileName":"card_normal", "logoResourceSetName":"event/the_whitest_day/images", "logoResourceFileName":"logo"
  },
  {
    "eventId":72, "introduction":"花咲川女子学園の修了式、香澄は全校生徒の前で『１年生代表のことば』を発表することに。修了式当日、壇上の香澄が語る言葉とは…", "resourceSetName":"characters/resourceset/res001030", "resourceFileName":"card_normal", "logoResourceSetName":"event/your_message/images", "logoResourceFileName":"logo"
  },
  {
    "eventId":73, "introduction":"ライブのセットリスト作りを依頼された各バンドのメンバー。それぞれのテーマを元に、思い思いのやり方でセットリストを作っていく。完成したリストにはどんな曲が…？", "resourceSetName":"characters/resourceset/res002026", "resourceFileName":"card_normal", "logoResourceSetName":"event/back_stage_pass2/images", "logoResourceFileName":"logo"
  },
  {
    "eventId":74, "introduction":"お花見の幹事を引き受けることになった彩と花音。順調に準備を進めているつもりの二人だが、周りにはそうは見えていないようで…", "resourceSetName":"characters/resourceset/res016033", "resourceFileName":"card_normal", "logoResourceSetName":"event/full_blooming/images", "logoResourceFileName":"logo"
  },
  {
    "eventId":75, "introduction":"高校２年生になったAfterglow。新しい教室、新しいクラスメイト、新しい毎日。再び同じクラスに集まったAfterglowの新たなる学園生活が始まる――", "resourceSetName":"characters/resourceset/res006033", "resourceFileName":"card_normal", "logoResourceSetName":"event/season_sky/images", "logoResourceFileName":"logo"
  },
  {
    "eventId":76, "introduction":"まだまだ生徒会の雰囲気に慣れない燐子。まずは生徒会内で緊張せずに話せる相手を作ろうと、有咲と仲良くなることを決意する。", "resourceSetName":"characters/resourceset/res025026", "resourceFileName":"card_normal", "logoResourceSetName":"event/bloom_flower/images", "logoResourceFileName":"logo"
  },
  {
    "eventId":77, "introduction":"ある晩、墜落するUFOを目撃したパスパレメンバー。UFOの落ちた場所で彼女達が目にしたものとは…？", "resourceSetName":"characters/resourceset/res017028", "resourceFileName":"card_normal", "logoResourceSetName":"event/underground_people/images", "logoResourceFileName":"logo"
  },
  {
    "eventId":78, "introduction":"クラスメイトとの会話をきっかけに、自分の思う『カッコいい』をみんなに伝えられるようになると決意したあこ。はたしてあこの『カッコいい』は伝わるのか…？", "resourceSetName":"characters/resourceset/res024030", "resourceFileName":"card_normal", "logoResourceSetName":"event/darkness_bluerose/images", "logoResourceFileName":"logo"
  },
  {
    "eventId":79, "introduction":"街の笑顔を守るため『笑顔パトロール隊』を結成したハロハピメンバー。あらゆる現場へと駆けつけ人々の笑顔を守り抜く。こころ達の笑顔の力は徐々に大きくなり…", "resourceSetName":"characters/resourceset/res011037", "resourceFileName":"card_normal", "logoResourceSetName":"event/smile_patrol/images", "logoResourceFileName":"logo"
  },
  {
    "eventId":80, "introduction":"「私の…結婚式に来ていただけないでしょうか！？」イヴの口から飛び出した衝撃の言葉に香澄は動揺が止まらない！", "resourceSetName":"characters/resourceset/res020032", "resourceFileName":"card_normal", "logoResourceSetName":"event/flowery_blide/images", "logoResourceFileName":"logo"
  },
  {
    "eventId":81, "introduction":"フェスに向けての申し込みが迫っているにも関わらず、普段通りの友希那に不安になるリサは――？", "resourceSetName":"characters/resourceset/res021028", "resourceFileName":"card_normal", "logoResourceSetName":"event/noble_rose/images", "logoResourceFileName":"logo"
  },
  {
    "eventId":82, "introduction":"暗いショッピングモールで『何か』から逃げるりみと美咲。彼女達の身に何が起こったのか？いったい何から逃げているのか？", "resourceSetName":"characters/resourceset/res015036", "resourceFileName":"card_normal", "logoResourceSetName":"event/band_of_dead/images", "logoResourceFileName":"logo"
  },
  {
    "eventId":83, "introduction":"一週間後に迫った、ポピパにとってとても大切な日。その日をお祝いするべく有咲とたえは、あるサプライズを準備することに。", "resourceSetName":"characters/resourceset/res005035", "resourceFileName":"card_normal", "logoResourceSetName":"event/spend_day_off/images", "logoResourceFileName":"logo"
  },
  {
    "eventId":84, "introduction":"フリマで偶然手に入れた非売品のCD。それを聴いた麻弥と友希那は、ある曲に心を奪われる。希望に満ちたその曲の魅力は、周りを巻き込み思いがけない展開へと…", "resourceSetName":"characters/resourceset/res019030", "resourceFileName":"card_normal", "logoResourceSetName":"event/hopefull_session/images", "logoResourceFileName":"logo"
  },
  {
    "eventId":85, "introduction":"ある日スマートにトラブルを解決するリサを見たひまりは、自分もリサのような頼れるカッコいい先輩になることを決意するが…？", "resourceSetName":"characters/resourceset/res008030", "resourceFileName":"card_normal", "logoResourceSetName":"event/stand_by_you/images", "logoResourceFileName":"logo"
  },
  {
    "eventId":86, "introduction":"夏の大きな仕事を終え、オフに入ったパスパレ一同。せっかくの揃ってのお休み、みんなで出かけることになり――？", "resourceSetName":"characters/resourceset/res018027", "resourceFileName":"card_normal", "logoResourceSetName":"event/summer_vacation/images", "logoResourceFileName":"logo"
  },
  {
    "eventId":87, "introduction":"薫の誘いで湖の畔に建つ別荘へとやってきたイヴ達。ゆったりとした時間の流れは、自然とみんなを笑顔にさせて…", "resourceSetName":"characters/resourceset/res020035", "resourceFileName":"card_normal", "logoResourceSetName":"event/summer_resort/images", "logoResourceFileName":"logo"
  },
  {
    "eventId":88, "introduction":"夏休みの宿題『俳句』に悩む美咲、こころ、はぐみ。俳句の題材探しを兼ねて、ハロハピの五人で花火大会に向かうことになり――？", "resourceSetName":"characters/resourceset/res014033", "resourceFileName":"card_normal", "logoResourceSetName":"event/harohapi_yukata/images", "logoResourceFileName":"logo"
  },
  {
    "eventId":89, "introduction":"目標であるフェス出場。でも『その先』はどうすればいいのか、あこはひとり思い悩む。モヤモヤを抱えたまま、フェス出場を賭けたコンテストが迫り…", "resourceSetName":"characters/resourceset/res025029", "resourceFileName":"card_normal", "logoResourceSetName":"event/noble_rose_2nd/images", "logoResourceFileName":"logo"
  },
  {
    "eventId":90, "introduction":"楽しい学校生活のため、生徒からの要望を実現しようとする羽丘生徒会。『るんっ♪』ときた案を全て採用しようとする日菜に、つぐみは振り回されっぱなしで――？", "resourceSetName":"characters/resourceset/res017031", "resourceFileName":"card_normal", "logoResourceSetName":"event/student_council_hane/images", "logoResourceFileName":"logo"
  },
  {
    "eventId":91, "introduction":"花女生徒会による『百人一首大会』が開催決定！大会の準備に頭を悩ませる紗夜だが、ふと同じように悩んでいる彩に気がつき――？", "resourceSetName":"characters/resourceset/res016041", "resourceFileName":"card_normal", "logoResourceSetName":"event/one_hundred_people/images", "logoResourceFileName":"logo"
  },
  {
    "eventId":92, "introduction":"街はハロウィン。ウキウキな香澄の提案で、ポピパは仮装パレードへ参加することに。思い思いの変身を遂げ、五人が非日常の先で目にするのは――？", "resourceSetName":"characters/resourceset/res005036", "resourceFileName":"card_normal", "logoResourceSetName":"event/popipa_halloween/images", "logoResourceFileName":"logo"
  },
  {
    "eventId":93, "introduction":"手作りマーケットに参加することになった美咲とリサ達。そのイベントに持っていく作品を作るため、リサの家に集まるが…", "resourceSetName":"characters/resourceset/res023035", "resourceFileName":"card_normal", "logoResourceSetName":"event/farmer_market/images", "logoResourceFileName":"logo"
  },
  {
    "eventId":94, "introduction":"華道の作品展のため、蘭がバンドを休むことに。進み続ける蘭に対し、どう向き合うべきかわからなくなるモカ。作品に込められたメッセージから、モカが出した答えとは――？", "resourceSetName":"characters/resourceset/res007030", "resourceFileName":"card_normal", "logoResourceSetName":"event/ranmoka_sazanka/images", "logoResourceFileName":"logo"
  },
  {
    "eventId":95, "introduction":"海外留学中の姉のゆりに、ビデオメッセージで紅葉を見せてあげたいと思ったりみ。はぐみが近くに紅葉のキレイな森林公園があると教えてくれて…", "resourceSetName":"characters/resourceset/res003033", "resourceFileName":"card_normal", "logoResourceSetName":"event/rimihagu_momiji/images", "logoResourceFileName":"logo"
  },
  {
    "eventId":96, "introduction":"イヴ、千聖、麻弥、日菜で彩の密着取材を行うことに。取材に意気込む彩だが、緊張して硬くなってしまい…！？", "resourceSetName":"characters/resourceset/res016043", "resourceFileName":"card_normal", "logoResourceSetName":"event/ayaeve_pasupare/images", "logoResourceFileName":"logo"
  },
  {
    "eventId":97, "introduction":"体験型テーマパークで、NFOのコラボイベントに参加するRoselia。クリア条件は全ミッションの達成。知恵と勇気を振り絞り、五人が辿り着いた結末とは――？", "resourceSetName":"characters/resourceset/res021034", "resourceFileName":"card_normal", "logoResourceSetName":"event/roselia_rezero/images", "logoResourceFileName":"logo"
  },
  {
    "eventId":98, "introduction":"もうすぐクリスマス。ハロハピもサンタさんを呼んでパーティしよう！と盛り上がる。その中でもひときわ張り切るはぐみ、それにはある理由があって…？", "resourceSetName":"characters/resourceset/res013035", "resourceFileName":"card_normal", "logoResourceSetName":"event/harohapi_christmas/images", "logoResourceFileName":"logo"
  },
  {
    "eventId":99, "introduction":"見慣れた日常も見方を変えれば楽しいものがいっぱい！私、嫌われちゃった…たえの一言をきっかけに、ひまり達の楽しいもの探しが始まる――", "resourceSetName":"characters/resourceset/res008035", "resourceFileName":"card_normal", "logoResourceSetName":"event/taehima_sensei/images", "logoResourceFileName":"logo"
  },
  {
    "eventId":100, "introduction":"演劇部の公演で、薫はかつて千聖が演じた役をやることに。その役には、千聖と薫が『役者』となった、あるエピソードが秘められていた。", "resourceSetName":"characters/resourceset/res018032", "resourceFileName":"card_normal", "logoResourceSetName":"event/kaochisa_child/images", "logoResourceFileName":"logo"
  },
  {
    "eventId":101, "introduction":"お正月、巴の太鼓の応援のために、神社へとやってきたあこ達。各々の初夢について話していると、その夢が一つずつ実現していき…？", "resourceSetName":"characters/resourceset/res024034", "resourceFileName":"card_normal", "logoResourceSetName":"event/ranako_newyear/images", "logoResourceFileName":"logo"
  },
  {
    "eventId":102, "introduction":"香澄とりみが蔵で勉強をしていると、かすかに扉が開く音が。そこにはブリキのおもちゃが置かれていて…？", "resourceSetName":"characters/resourceset/res003034", "resourceFileName":"card_normal", "logoResourceSetName":"event/kasurimi_popipa/images", "logoResourceFileName":"logo"
  },
  {
    "eventId":103, "introduction":"モカの誘いで、中華街へ遊びに行くことになったリサ。\n美味しい料理に想いを馳せるうち、気づけばこころ達も加わって大所帯に…？", "resourceSetName":"characters/resourceset/res023037", "resourceFileName":"card_normal", "logoResourceSetName":"event/kokorisa_oldsyogatu/images", "logoResourceFileName":"logo"
  },
  {
    "eventId":104, "introduction":"番組の企画で、日菜にバレンタインチョコをプレゼントすることになった麻弥達。果たして、日菜が欲しがる『るるるんっ♪　としたチョコ』を作れるのか……？", "resourceSetName":"characters/resourceset/res017037", "resourceFileName":"card_normal", "logoResourceSetName":"event/pspr_valentine/images", "logoResourceFileName":"logo"
  },
  {
    "eventId":105, "introduction":"いよいよFWFを目前に控えたRoselia。友希那はこれからの自分達にふさわしい新曲を完成させるべく、これまでの歩みを振り返る――", "resourceSetName":"characters/resourceset/res021035", "resourceFileName":"card_normal", "logoResourceSetName":"event/noble_rose_3rd/images", "logoResourceFileName":"logo"
  },
  {
    "eventId":106, "introduction":"駅前のストリートライブ。花音はその光景と、昔こころとやったストリートライブを重ね合わせる。またやってみたい。そんな花音の言葉を、隣で聞いていた有咲は――", "resourceSetName":"characters/resourceset/res014037", "resourceFileName":"card_normal", "logoResourceSetName":"event/kanoarisa_street/images", "logoResourceFileName":"logo"
  },
  {
    "eventId":107, "introduction":"ホワイトデーが迫ったある日、巴はお返しについてAfterglowのメンバーに相談する。お返しをする相手の多さに悩む巴。そんな巴をつぐみが手伝うことに――", "resourceSetName":"characters/resourceset/res009036", "resourceFileName":"card_normal", "logoResourceSetName":"event/afuro_whiteday/images", "logoResourceFileName":"logo"
  },
  {
    "eventId":108, "introduction":"何気ない会話から、新しい趣味探しを思いつく沙綾。偶然居合わせたモカと一緒に、新たな趣味候補に挑戦するのだが――", "resourceSetName":"characters/resourceset/res004033", "resourceFileName":"card_normal", "logoResourceSetName":"event/mokasaaya_photo/images", "logoResourceFileName":"logo"
  },
  {
    "eventId":109, "introduction":"CiRCLEのホームページリニューアルを控え、まりなは各バンドに協力を仰ぐ。まりなのインタビューに答えながら、自分達の活動をそれぞれ振り返り…", "resourceSetName":"characters/resourceset/res003036", "resourceFileName":"card_normal", "logoResourceSetName":"event/3rd_omnibus/images", "logoResourceFileName":"logo"
  },
  {
    "eventId":110, "introduction":"ひょんなことから、はぐみのチームでソフトボールをすることになったハロハピ一同。練習試合に向けて奮闘するも、各々のプレーには課題があるようで…？", "resourceSetName":"characters/resourceset/res013039", "resourceFileName":"card_normal", "logoResourceSetName":"event/kaohagu_harohapi/images", "logoResourceFileName":"logo"
  },
  {
    "eventId":111, "introduction":"ポピパからお花見に誘われたモニカ。当日、なんと６バンド大集合のお花見だと判明する。これを機に、先輩バンドと仲良くなろうと意気込むモニカのメンバーだったが…！？", "resourceSetName":"characters/resourceset/res026005", "resourceFileName":"card_normal", "logoResourceSetName":"event/monica_symphony/images", "logoResourceFileName":"logo"
  },
  {
    "eventId":112, "introduction":"単発ドラマのオーディション候補に選ばれた千聖。パスパレのメンバーが激励していると、もう一人候補者がいることを知る。そのもう一人とは…？", "resourceSetName":"characters/resourceset/res018038", "resourceFileName":"card_normal", "logoResourceSetName":"event/play_act/images", "logoResourceFileName":"logo"
  },
  {
    "eventId":113, "introduction":"ドームで開催するライブイベント『ガールズバンドEXPO』を観に行くことになった香澄、蘭、友希那、彩、こころの五人。\n会場では、さらなる出会いが待っていて…？", "resourceSetName":"characters/resourceset/res001044", "resourceFileName":"card_normal", "logoResourceSetName":"event/gbp_kinen_2020/images", "logoResourceFileName":"logo"
  },
  {
    "eventId":114, "introduction":"偶然出会った七深の探し物を手伝うことになった有咲。しかし彼女が探しているお菓子は、どうやら普通じゃないようで――！？", "resourceSetName":"characters/resourceset/res028006", "resourceFileName":"card_normal", "logoResourceSetName":"event/lets_collection/images", "logoResourceFileName":"logo"
  },
  {
    "eventId":115, "introduction":"いつも通りのライブを成功させたAfterglow。しかし、つぐみの胸にはもやもやした感情が燻っていた。ふと頭を過ったのはFWFのRoseliaの姿で――", "resourceSetName":"characters/resourceset/res010041", "resourceFileName":"card_normal", "logoResourceSetName":"event/scorch_sky/images", "logoResourceFileName":"logo"
  },
  {
    "eventId":116, "introduction":"再び全員揃ってNFOをプレイすることになったRoselia。限定イベントを無事クリアして、ドラゴンから花嫁を守り抜くことはできるのか――！？", "resourceSetName":"characters/resourceset/res025036", "resourceFileName":"card_normal", "logoResourceSetName":"event/roselia_wedding/images", "logoResourceFileName":"logo"
  },
  {
    "eventId":118, "introduction":"雨の日の剣道部。練習試合に勝利したイヴは、ブシドーの境地に近づいてきていると自信を持つ。しかし顧問の先生から言われたのは、イヴにとって意外な言葉で――", "resourceSetName":"characters/resourceset/res020043", "resourceFileName":"card_normal", "logoResourceSetName":"event/eve_nayami/images", "logoResourceFileName":"logo"
  },
  {
    "eventId":119, "introduction":"地域の学校全てが参加する大合同体育祭が開幕！　実行委員を務めるポピパのみんなは、大合同体育祭を盛り上げるため、実行委員のお仕事に奮闘していくが…？", "resourceSetName":"characters/resourceset/res005043", "resourceFileName":"card_normal", "logoResourceSetName":"event/railgun_2020/images", "logoResourceFileName":"logo"
  },
  {
    "eventId":120, "introduction":"学園で注目の的となったMorfonica。しかし、褒められているのは瑠唯ばかり。納得できない透子は新曲の見せ場が欲しいと言い出し、二人はケンカに――！？", "resourceSetName":"characters/resourceset/res030006", "resourceFileName":"card_normal", "logoResourceSetName":"event/monica_ecude/images", "logoResourceFileName":"logo"
  },
  {
    "eventId":121, "introduction":"夏の太陽が勢いを増すある日、ハロハピのメンバー五人は夏休みの活動について話し合っていた。そこではぐみがカレーを食べたいと言い出し――", "resourceSetName":"characters/resourceset/res015045", "resourceFileName":"card_normal", "logoResourceSetName":"event/niconico_natsuyasumi/images", "logoResourceFileName":"logo"
  },
  {
    "eventId":122, "introduction":"夏休み、猛練習を続けるAfterglow。気分転換にどこかに遊びに行こう、というひまりの提案で行くことになったのは、あの夏のテーマパーク！", "resourceSetName":"characters/resourceset/res007036", "resourceFileName":"card_normal", "logoResourceSetName":"event/afterglow_summer2020/images", "logoResourceFileName":"logo"
  },
  {
    "eventId":123, "introduction":"紗夜は、偶然訪れた店で大きなため息をつく透子を見かける。透子に泣きつかれて、ギターを教えることになった紗夜は――！？", "resourceSetName":"characters/resourceset/res022039", "resourceFileName":"card_normal", "logoResourceSetName":"event/guiter_lesson/images", "logoResourceFileName":"logo"
  },
  {
    "eventId":124, "introduction":"海の中にあるポストがある？　たえ、日菜、香澄、麻弥、リサは、そんな珍しい海へ遊びに行くことに。さあ、みんなで最高の夏の思い出を作ろう…！", "resourceSetName":"characters/resourceset/res002039", "resourceFileName":"card_normal", "logoResourceSetName":"event/ocean_post/images", "logoResourceFileName":"logo"
  },
  {
    "eventId":126, "introduction":"事務所の研究生が、パスパレのライブに出演することに。研究生のライブでの様子を見て、麻弥たちは合同レッスンの開催を提案して…？", "resourceSetName":"characters/resourceset/res019041", "resourceFileName":"card_normal", "logoResourceSetName":"event/brighter_britghter/images", "logoResourceFileName":"logo"
  },
  {
    "eventId":127, "introduction":"FWF後、音楽事務所への所属を誘われることが増えたRoselia。スカウトを断り続けていたら、今度はプロのミュージシャンからツーマンライブの誘いがあって――！？", "resourceSetName":"characters/resourceset/res021042", "resourceFileName":"card_normal", "logoResourceSetName":"event/roselia_pro/images", "logoResourceFileName":"logo"
  },
  {
    "eventId":128, "introduction":"『ハロウィンフェスティバル』が開催されることになった羽丘女子学園。憧れの香澄も来ると知ったロックは――！？", "resourceSetName":"characters/resourceset/res032006", "resourceFileName":"card_normal", "logoResourceSetName":"event/lock_halloween/images", "logoResourceFileName":"logo"
  },
  {
    "eventId":130, "introduction":"蔵で練習していたポピパは、休憩中に学校行事の話をする。有咲に、今年は花女のパンフレットを作り直すと聞いた香澄達は…？", "resourceSetName":"characters/resourceset/res004037", "resourceFileName":"card_normal", "logoResourceSetName":"event/popipa_memories/images", "logoResourceFileName":"logo"
  },
  {
    "eventId":131, "introduction":"『魔女のお店』があるという噂を聞きつけたはぐみ。もしかしたら、本物の魔女に会えるかも！？　そんな期待を胸に、ハロハピのメンバーと共に店へと向かうのだが…？", "resourceSetName":"characters/resourceset/res011049", "resourceFileName":"card_normal", "logoResourceSetName":"event/witch_2020/images", "logoResourceFileName":"logo"
  },
  {
    "eventId":132, "introduction":"ついに憧れのCiRCLEでライブをすることになったMorfonica！\n興奮を隠せない七深や透子とは対照的に、ましろとつくしはどこか不安そうで…？", "resourceSetName":"characters/resourceset/res026008", "resourceFileName":"card_normal", "logoResourceSetName":"event/monica_einsatz/images", "logoResourceFileName":"logo"
  },
  {
    "eventId":133, "introduction":"ガールズバンドチャレンジを終え、絆が強まったRAS。次に目指すはワンマンライブの大成功。しかしチュチュの指摘から、レイヤ自身に『ある問題』が浮上して――！？", "resourceSetName":"characters/resourceset/res031006", "resourceFileName":"card_normal", "logoResourceSetName":"event/no_border/images", "logoResourceFileName":"logo"
  },
  {
    "eventId":134, "introduction":"クリスマスイブを共に過ごす約束をした紗夜と日菜。なにをして遊ぼう、プレゼント交換はどうしよう。大喜びする日菜だったが、紗夜には隠し事があるようで――", "resourceSetName":"characters/resourceset/res022041", "resourceFileName":"card_normal", "logoResourceSetName":"event/xmas_2020/images", "logoResourceFileName":"logo"
  },
  {
    "eventId":136, "introduction":"ガルジャムの熱がいまだ続くAfterglow。気合いの入った練習を続けていたある日、巴にインタビューの依頼が舞い込む。その様子を見守るつぐみは――", "resourceSetName":"characters/resourceset/res009043", "resourceFileName":"card_normal", "logoResourceSetName":"event/tomoe_interview/images", "logoResourceFileName":"logo"
  },
  {
    "eventId":137, "introduction":"巴から頼まれ、リサと一緒に巫女の助勤をやることになった有咲。当日、不安に思いながらも待ち合わせ場所で待っていると、そこに現れたのはリサではなく友希那で――！？", "resourceSetName":"characters/resourceset/res021043", "resourceFileName":"card_normal", "logoResourceSetName":"event/new_year_2021/images", "logoResourceFileName":"logo"
  },
  {
    "eventId":138, "introduction":"『和』をテーマにしたイベントへの出演が決まった蘭。生け花と着物、両方のPRのため、協力者と共に計画を練ることになるのだが、果たして…？", "resourceSetName":"characters/resourceset/res006050", "resourceFileName":"card_normal", "logoResourceSetName":"event/rantoko_ikebana/images", "logoResourceFileName":"logo"
  },
  {
    "eventId":139, "introduction":"『助けて』――。突然、燐子とあこのもとに、この通知がリサから届く。二人が急いでリサの家に向かうと、何やら不思議なことが起き始めて…？", "resourceSetName":"characters/resourceset/res023048", "resourceFileName":"card_normal", "logoResourceSetName":"event/lisaako_otomari/images", "logoResourceFileName":"logo"
  },
  {
    "eventId":140, "introduction":"我慢した分だけお菓子は美味しくなる。りみからこの話を聞いた香澄達は、バレンタインまでお菓子断ちをすることに！けれど甘～い誘惑がポピパを翻弄してきて…！？", "resourceSetName":"characters/resourceset/res003040", "resourceFileName":"card_normal", "logoResourceSetName":"event/popipa_valentine/images", "logoResourceFileName":"logo"
  },
  {
    "eventId":142, "introduction":"セッションに熱中しすぎて音が合わなくなってしまったロックとマスキング。一緒に過ごす時間を増やせば音合わせの精度が上がるかもというアドバイスを受けた二人は――", "resourceSetName":"characters/resourceset/res033008", "resourceFileName":"card_normal", "logoResourceSetName":"event/maslock_play/images", "logoResourceFileName":"logo"
  }
]
