{
  "entries":{
    "1":{
      "bandStoryChapterId":1, "bandId":1, "bandStoryChapterType":"chapter_1", "seq":10, "mainTitle":"1章", "subTitle":"Colorful☆Poppin'Candy", "publishedAt":29589788544, "closedAt":282195840, "chapterNumber":1, "masterBandStoryChapterDetailList":[
        
      ]
    },
    "2":{
      "bandStoryChapterId":2, "bandId":2, "bandStoryChapterType":"chapter_1", "seq":10, "mainTitle":"1章", "subTitle":"\"いつも通り\"のAfterglow", "publishedAt":29589788544, "closedAt":282195840, "chapterNumber":1, "masterBandStoryChapterDetailList":[
        
      ]
    },
    "3":{
      "bandStoryChapterId":3, "bandId":3, "bandStoryChapterType":"chapter_1", "seq":10, "mainTitle":"1章", "subTitle":"世界を笑顔に！　ハロハピ結成！", "publishedAt":29589788544, "closedAt":282195840, "chapterNumber":1, "masterBandStoryChapterDetailList":[
        
      ]
    },
    "4":{
      "bandStoryChapterId":4, "bandId":4, "bandStoryChapterType":"chapter_1", "seq":10, "mainTitle":"1章", "subTitle":"Pastel＊Palettes、はじまりの物語", "publishedAt":29589788544, "closedAt":282195840, "chapterNumber":1, "masterBandStoryChapterDetailList":[
        
      ]
    },
    "5":{
      "bandStoryChapterId":5, "bandId":5, "bandStoryChapterType":"chapter_1", "seq":10, "mainTitle":"1章", "subTitle":"青い薔薇　芽吹く", "publishedAt":29589788544, "closedAt":282195840, "chapterNumber":1, "masterBandStoryChapterDetailList":[
        
      ]
    },
    "6":{
      "bandStoryChapterId":6, "bandId":1, "bandStoryChapterType":"chapter_0", "seq":5, "mainTitle":"0章", "subTitle":"Poppin'Party結成！", "publishedAt":12278311808, "closedAt":282195840, "chapterNumber":0, "masterBandStoryChapterDetailList":[
        
      ]
    },
    "7":{
      "bandStoryChapterId":7, "bandId":1, "bandStoryChapterType":"chapter_2", "seq":20, "mainTitle":"2章", "subTitle":"二重の虹（ダブル レインボウ）", "publishedAt":13239511808, "closedAt":282195840, "chapterNumber":2, "masterBandStoryChapterDetailList":{
        "entries":[
          {
            "bandStoryChapterDetailId":2, "bandStoryChapterId":7, "eventId":41, "startAt":13239511808, "endAt":14103511808, "supplement":"イベントTOP画面に遷移します", "appeal":"イベント先行公開中"
          },
          {
            "bandStoryChapterDetailId":3, "bandStoryChapterId":7, "releaseBandStoryId":20, "startAt":14103511808, "endAt":282195840, "releaseConditions":"バンドストーリー1章「第２０話」を見ると解放"
          }
        ]
      }
    },
    "8":{
      "bandStoryChapterId":8, "bandId":1, "seq":15, "mainTitle":"1章", "subTitle":"Colorful☆Poppin'Candy", "publishedAt":12980311808, "closedAt":14103511808, "masterBandStoryChapterDetailList":{
        "entries":[
          {
            "bandStoryChapterDetailId":1, "bandStoryChapterId":8, "startAt":12980311808, "endAt":14103511808, "supplement":"限定公開ストーリーに達成ボーナスはありません", "appeal":"全話限定公開中"
          }
        ]
      }
    },
    "9":{
      "bandStoryChapterId":9, "bandId":5, "bandStoryChapterType":"chapter_2", "seq":20, "mainTitle":"2章", "subTitle":"Neo-Aspect", "publishedAt":15053911808, "closedAt":282195840, "chapterNumber":2, "masterBandStoryChapterDetailList":{
        "entries":[
          {
            "bandStoryChapterDetailId":5, "bandStoryChapterId":9, "eventId":43, "startAt":15053911808, "endAt":15917911808, "supplement":"イベントTOP画面に遷移します", "appeal":"イベント先行公開中"
          },
          {
            "bandStoryChapterDetailId":6, "bandStoryChapterId":9, "releaseBandStoryId":100, "startAt":15917911808, "endAt":282195840, "releaseConditions":"バンドストーリー1章「第２０話」を見ると解放"
          }
        ]
      }
    },
    "10":{
      "bandStoryChapterId":10, "bandId":5, "seq":15, "mainTitle":"1章", "subTitle":"青い薔薇　芽吹く", "publishedAt":14881111808, "closedAt":15917911808, "masterBandStoryChapterDetailList":{
        "entries":[
          {
            "bandStoryChapterDetailId":4, "bandStoryChapterId":10, "startAt":14881111808, "endAt":15917911808, "supplement":"限定公開ストーリーに達成ボーナスはありません", "appeal":"全話限定公開中"
          }
        ]
      }
    },
    "11":{
      "bandStoryChapterId":11, "bandId":4, "seq":15, "mainTitle":"1章", "subTitle":"Pastel＊Palettes、はじまりの物語", "publishedAt":17473111808, "closedAt":18509911808, "masterBandStoryChapterDetailList":{
        "entries":[
          {
            "bandStoryChapterDetailId":7, "bandStoryChapterId":11, "startAt":17473111808, "endAt":18509911808, "supplement":"限定公開ストーリーに達成ボーナスはありません", "appeal":"全話限定公開中"
          }
        ]
      }
    },
    "12":{
      "bandStoryChapterId":12, "bandId":4, "bandStoryChapterType":"chapter_2", "seq":20, "mainTitle":"2章", "subTitle":"もういちど ルミナス", "publishedAt":17645911808, "closedAt":282195840, "chapterNumber":2, "masterBandStoryChapterDetailList":{
        "entries":[
          {
            "bandStoryChapterDetailId":8, "bandStoryChapterId":12, "eventId":46, "startAt":17645911808, "endAt":18509911808, "supplement":"イベントTOP画面に遷移します", "appeal":"イベント先行公開中"
          },
          {
            "bandStoryChapterDetailId":9, "bandStoryChapterId":12, "releaseBandStoryId":80, "startAt":18509911808, "endAt":282195840, "releaseConditions":"バンドストーリー1章「第２０話」を見ると解放"
          }
        ]
      }
    }
  }
}
